streamapp/__init__.py
streamapp/cards.py
streamapp/enviroment_selector.py
streamapp/report_generator.py
streamapp/requests.py
streamapp/snow_class.py
streamapp/subpages.py
streamapp/utils.py
streamapp/validators.py
streamapp/auth/__init__.py
streamapp/auth/authenticator.py
streamapp/auth/mongo_auth.py
streamapp/auth/roles.py
streamapp/auth/user_panel.py
streamapp-0.0.13.dist-info/licenses/LICENSE
streamapp-0.0.13.dist-info/METADATA
streamapp-0.0.13.dist-info/WHEEL
streamapp-0.0.13.dist-info/top_level.txt
streamapp-0.0.13.dist-info/RECORD
