Metadata-Version: 2.4
Name: streamapp
Version: 0.0.13
Summary: Base modules to use in a Streamlit basic project
Home-page: https://github.com/nmrls/streamapp_utils
Author: nmrls
License: MIT License
Classifier: Development Status :: 1 - Planning
Classifier: Intended Audience :: Science/Research
Classifier: License :: OSI Approved :: MIT License
Classifier: Operating System :: OS Independent
Classifier: Programming Language :: Python :: 3
Requires-Python: >=3.10.0
License-File: LICENSE
Requires-Dist: streamlit>=1.30.0
Requires-Dist: pydantic>=2.5.3
Requires-Dist: openpyxl==3.1.2
Requires-Dist: snowflake-connector-python>=3.0.4
Requires-Dist: streamlit-authenticator==0.3.2
Requires-Dist: pymongo==4.6.3
Requires-Dist: twine>=4.0.2
Dynamic: author
Dynamic: classifier
Dynamic: description
Dynamic: description-content-type
Dynamic: home-page
Dynamic: license
Dynamic: license-file
Dynamic: requires-dist
Dynamic: requires-python
Dynamic: summary
